mediapy/__init__.py
mediapy/py.typed
mediapy-1.2.5.dist-info/licenses/LICENSE
mediapy-1.2.5.dist-info/WHEEL
mediapy-1.2.5.dist-info/METADATA
mediapy-1.2.5.dist-info/RECORD
