Metadata-Version: 2.4
Name: mediapy
Version: 1.2.5
Summary: Read/write/show images and videos in an IPython notebook
Keywords: 
Author-email: Google LLC <mediapy-owners@google.com>
Requires-Python: >=3.8
Classifier: Programming Language :: Python :: 3
Classifier: License :: OSI Approved :: Apache Software License
Classifier: Operating System :: OS Independent
Classifier: Framework :: IPython
Classifier: Framework :: Jupyter
Classifier: Topic :: Multimedia :: Graphics :: Viewers
Classifier: Topic :: Multimedia :: Video :: Display
License-File: LICENSE
Requires-Dist: ipython
Requires-Dist: matplotlib
Requires-Dist: numpy
Requires-Dist: Pillow
Requires-Dist: absl-py ; extra == "dev"
Requires-Dist: pyink ; extra == "dev"
Requires-Dist: pylint>=2.6.0 ; extra == "dev"
Requires-Dist: pytest ; extra == "dev"
Requires-Dist: pytest-xdist ; extra == "dev"
Requires-Dist: pytype ; extra == "dev"
Project-URL: homepage, https://github.com/google/mediapy
Project-URL: repository, https://github.com/google/mediapy
Provides-Extra: dev
